esbmc_ai/__about__.py
esbmc_ai/__init__.py
esbmc_ai/__main__.py
esbmc_ai/ai_models.py
esbmc_ai/api_key_collection.py
esbmc_ai/base_chat_interface.py
esbmc_ai/chat_response.py
esbmc_ai/config.py
esbmc_ai/esbmc_util.py
esbmc_ai/latest_state_solution_generator.py
esbmc_ai/loading_widget.py
esbmc_ai/logging.py
esbmc_ai/msg_bus.py
esbmc_ai/optimize_code.py
esbmc_ai/reverse_order_solution_generator.py
esbmc_ai/solution_generator.py
esbmc_ai/user_chat.py
esbmc_ai/commands/__init__.py
esbmc_ai/commands/chat_command.py
esbmc_ai/commands/exit_command.py
esbmc_ai/commands/fix_code_command.py
esbmc_ai/commands/help_command.py
esbmc_ai/frontend/__init__.py
esbmc_ai/frontend/solution.py
esbmc_ai-0.5.1.dist-info/METADATA
esbmc_ai-0.5.1.dist-info/WHEEL
esbmc_ai-0.5.1.dist-info/entry_points.txt
esbmc_ai-0.5.1.dist-info/licenses/LICENSE
esbmc_ai-0.5.1.dist-info/RECORD
