Metadata-Version: 2.3
Name: esbmc_ai
Version: 0.5.1
Summary: LLM driven development and automatic repair kit.
Project-URL: Homepage, https://github.com/Yiannis128/esbmc-ai
Project-URL: Source Code, https://github.com/Yiannis128/esbmc-ai
Project-URL: Documentation, https://github.com/Yiannis128/esbmc-ai/wiki
Project-URL: Issues, https://github.com/Yiannis128/esbmc-ai/issues
Author-email: Yiannis Charalambous <yiannis128@hotmail.com>
License-File: LICENSE
Keywords: AI,LLM,automated code repair,esbmc
Classifier: License :: OSI Approved :: GNU Affero General Public License v3
Classifier: Programming Language :: Python :: 3
Requires-Python: >=3.10
Requires-Dist: aiohttp
Requires-Dist: aiosignal
Requires-Dist: async-timeout
Requires-Dist: attrs
Requires-Dist: certifi
Requires-Dist: charset-normalizer
Requires-Dist: clang
Requires-Dist: frozenlist
Requires-Dist: idna
Requires-Dist: langchain
Requires-Dist: langchain-openai
Requires-Dist: libclang
Requires-Dist: multidict
Requires-Dist: openai
Requires-Dist: python-dotenv
Requires-Dist: regex
Requires-Dist: requests
Requires-Dist: tiktoken
Requires-Dist: urllib3
Requires-Dist: yarl
